ostrich/__init__.py
ostrich/utils/__init__.py
ostrich/utils/collections.py
ostrich/utils/path.py
ostrich/utils/proc.py
ostrich/utils/text.py
ostrichlib-0.1.dist-info/DESCRIPTION.rst
ostrichlib-0.1.dist-info/METADATA
ostrichlib-0.1.dist-info/RECORD
ostrichlib-0.1.dist-info/WHEEL
ostrichlib-0.1.dist-info/metadata.json
ostrichlib-0.1.dist-info/top_level.txt
ostrichlib-0.1.dist-info/zip-safe
scripts/__init__.py
scripts/gh_release.py
scripts/make_rel_msg.py
